yaml_indent/__init__.py
yaml_indent/_version.py
yaml_indent/yaml_indent.py
yaml_indent-0.1.4.dist-info/entry_points.txt
yaml_indent-0.1.4.dist-info/WHEEL
yaml_indent-0.1.4.dist-info/METADATA
yaml_indent-0.1.4.dist-info/LICENSE
yaml_indent-0.1.4.dist-info/RECORD
