Metadata-Version: 2.1
Name: yaml-indent
Version: 0.1.4
Summary: Tool for making consistent indentation
Author: Knut Olav Bøhmer
Author-email: bohmer@gmail.com
Requires-Python: >=3.10,<4.0
Classifier: Programming Language :: Python :: 3
Classifier: Programming Language :: Python :: 3.10
Classifier: Programming Language :: Python :: 3.11
Requires-Dist: argparse (>=1.4.0,<2.0.0)
Requires-Dist: configparser (>=5.3.0,<6.0.0)
Requires-Dist: ruamel-yaml (>=0.17.31,<0.18.0)
Requires-Dist: toml (>=0.10.2,<0.11.0)
Project-URL: Bug Tracker, https://github.com/knobo/yaml-indent/issues
Project-URL: Documentation, https://github.com/knobo/yaml-indent/wiki
Project-URL: Repository, https://github.com/knobo/yaml-indent
